grove/__init__.py
grove/grove.py
panda_grove-0.1.4.dist-info/LICENSE
panda_grove-0.1.4.dist-info/METADATA
panda_grove-0.1.4.dist-info/WHEEL
panda_grove-0.1.4.dist-info/top_level.txt
panda_grove-0.1.4.dist-info/RECORD
