Metadata-Version: 2.1
Name: panda-grove
Version: 0.1.4
Summary: A lightweight package for easier management of multiple Pandas DataFrames
Author: Filip Buric
Maintainer: Filip Buric
License: BSD 3-Clause License
Project-URL: Homepage, https://panda-grove.readthedocs.io
Project-URL: Documentation, https://panda-grove.readthedocs.io
Project-URL: Repository, https://github.com/fburic/panda-grove
Project-URL: Issues, https://github.com/fburic/panda-grove/issues
Classifier: Environment :: Console
Classifier: Intended Audience :: Developers
Classifier: Intended Audience :: Education
Classifier: Intended Audience :: Science/Research
Classifier: Topic :: Database
Classifier: Topic :: Scientific/Engineering 
Classifier: License :: OSI Approved :: BSD License
Classifier: Programming Language :: Python :: 3
Classifier: Programming Language :: Python :: 3 :: Only
Requires-Python: >=3.7
License-File: LICENSE
Requires-Dist: pandas >=1.1.0
